LICENSE
MANIFEST.in
README.md
setup.py
django_setmagic.egg-info/PKG-INFO
django_setmagic.egg-info/SOURCES.txt
django_setmagic.egg-info/dependency_links.txt
django_setmagic.egg-info/requires.txt
django_setmagic.egg-info/top_level.txt
setmagic/__init__.py
setmagic/admin.py
setmagic/backend.py
setmagic/context_processors.py
setmagic/exceptions.py
setmagic/models.py
setmagic/tests.py
setmagic/wrapper.py
setmagic/migrations/0001_initial.py
setmagic/migrations/0002_setting_current_value.py
setmagic/migrations/0003_auto_20140709_1552.py
setmagic/migrations/0004_auto_20140710_2333.py
setmagic/migrations/0005_auto_20140711_0818.py
setmagic/migrations/0006_auto_20140711_1016.py
setmagic/migrations/0007_auto_20140713_0121.py
setmagic/migrations/0008_auto_20140714_0232.py
setmagic/migrations/__init__.py
setmagic/static/admin/setmagic.css
setmagic/templates/admin/setmagic/setting/change_list.html
setmagic/templatetags/__init__.py
setmagic/templatetags/setmagic.py