Metadata-Version: 1.1
Name: django-setmagic
Version: 0.3
Summary: Magically editable settings for winged pony lovers
Home-page: https://github.com/7ws/django-setmagic
Author: Evandro Myller
Author-email: emyller@7ws.co
License: UNKNOWN
Keywords: django,settings
Platform: UNKNOWN
Classifier: Framework :: Django
Classifier: License :: OSI Approved :: MIT License
Classifier: Programming Language :: Python
Classifier: Programming Language :: Python :: 2.6
Classifier: Programming Language :: Python :: 2.7
Classifier: Programming Language :: Python :: 3.1
Classifier: Programming Language :: Python :: 3.2
Classifier: Programming Language :: Python :: 3.3
Classifier: Programming Language :: Python :: 3.4
Classifier: Topic :: Software Development
